snapper/__init__.py
snapper/snapper.py
snapper/src/data_processing.py
snapper/src/methods.py
snapper/src/motif_extraction.py
snapper/src/plotting.py
snapper/src/seq_processing.py
snapper/src/statistics_methods.py
snapper/src/type_I_RM_system.py
snapper_ont-1.0.0.dist-info/LICENSE
snapper_ont-1.0.0.dist-info/METADATA
snapper_ont-1.0.0.dist-info/WHEEL
snapper_ont-1.0.0.dist-info/entry_points.txt
snapper_ont-1.0.0.dist-info/top_level.txt
snapper_ont-1.0.0.dist-info/RECORD
