Metadata-Version: 2.1
Name: snapper-ont
Version: 1.0.0
Summary: Nanopore-based methylation sites caller
Home-page: https://github.com/DNKonanov/Snapper
Author: D.N. Konanov
Author-email: konanovdmitriy@gmail.com
Project-URL: Bug Tracker, https://github.com/DNKonanov/Snapper
Classifier: Programming Language :: Python :: 3
Classifier: License :: OSI Approved :: MIT License
Classifier: Operating System :: OS Independent
Requires-Python: >=3.7
License-File: LICENSE
Requires-Dist: h5py
Requires-Dist: biopython
Requires-Dist: matplotlib
Requires-Dist: scipy
Requires-Dist: seaborn
Requires-Dist: tqdm
